ARES_KZ/__init__.py
ARES_KZ/factorsKZ.csv
ares_kz-3.0.0.dist-info/METADATA
ares_kz-3.0.0.dist-info/WHEEL
ares_kz-3.0.0.dist-info/top_level.txt
ares_kz-3.0.0.dist-info/RECORD
