Metadata-Version: 2.4
Name: ares-kz
Version: 3.0.0
Summary: Kazakhstan corporate credit risk factors
Author: Iskakov.Aryslan_AFR
License: MIT
Classifier: Programming Language :: Python :: 3
Requires-Python: >=3.7
